{"name":"GDeskTunes","tagline":"Desktop Player for Google Play Music™","body":"# Multi Platform Desktop Player \r\n# for Google Play Music™ \r\n# that integrates beatifully in your OS.\r\n\r\n![](https://raw.githubusercontent.com/gearlux/gdesktunes/gh-pages/pictures/gdesktunes_songs_spotify_black.png)\r\n\r\n## Download\r\nCheckout the [Downloads page](https://github.com/Gearlux/GDeskTunes/releases)\r\n\r\n## Features\r\n* **Media Keys**: Control your music without having to switch applications. Radiant Player responds to the media keys built in your computer, allowing you to easily control the playback of your music no matter what you're doing.\r\n* **Mini Layout**: Switch to a minimal layout so you can continue your work while viewing the song that is playing.\r\n* **Last.Fm Integration**: Update your Now Playing status and scrobble tracks to Last.fm.\r\n* **Custom Styles**: Use custom styles built into GDeskTunes to make it look beautiful, or stick with Google's original theme.\r\n* **Notification**: Get notifications whenever the currently playing song changes.\r\n* **Mini Player**: Access the mini player from your tray icon.\r\n\r\n## Credits\r\n\r\nNo affiliation with Google. Google Play is a trademark of Google Inc.\r\n\r\nGDeskTunes is inspired by [Radiant Player](http://kbhomes.github.io/radiant-player-mac/) and [Google Music Desktop Player](http://vhanla.deviantart.com/art/Google-Music-Desktop-Player-413683928)","google":"UA-57303126-1","note":"Don't delete this file! It's used internally to help with page regeneration."}